opentsdbproxy
