Metadata-Version: 1.0
Name: opentsdbproxy
Version: 0.1.2
Summary: Experimental proxy to add SSL and ACL to OpenTSDB
Home-page: UNKNOWN
Author: University of Chicago
Author-email: nimbus@mcs.anl.gov
License: Apache 2.0
Keywords: opentsdb
Platform: UNKNOWN
Classifier: Development Status :: 3 - Alpha
Classifier: Environment :: Console
Classifier: Intended Audience :: Developers
Classifier: License :: OSI Approved :: Apache Software License
Classifier: Operating System :: OS Independent
Classifier: Programming Language :: Python
Classifier: Topic :: Scientific/Engineering
